LICENSE
logmail/__init__.py
logmail/mailing.py
logmail-0.1.12.dist-info/LICENSE
logmail-0.1.12.dist-info/WHEEL
logmail-0.1.12.dist-info/METADATA
logmail-0.1.12.dist-info/RECORD
