Metadata-Version: 2.1
Name: logmail
Version: 0.1.12
Summary: Simple send mails as logging in Loguru
Home-page: https://github.com/DanilaCharushin/logmail
License: MIT
Keywords: mail,loguru,loguru for mail
Author: DanilaCharushin
Author-email: charushin2000@gmail.com
Requires-Python: >=3.8,<4.0
Classifier: License :: OSI Approved :: MIT License
Classifier: Operating System :: OS Independent
Classifier: Programming Language :: Python :: 3
Classifier: Programming Language :: Python :: 3.8
Classifier: Programming Language :: Python :: 3.9
Requires-Dist: emails (>=0.6,<0.7)
Requires-Dist: loguru (>=0.5.3,<0.6.0)
Project-URL: Repository, https://github.com/DanilaCharushin/logmail.git
